tppss/__init__.py
tppss/cli.py
tppss/horizon.py
tppss/sunpos.py
tppss/tppss.py
tppss-0.2.dist-info/LICENSE
tppss-0.2.dist-info/METADATA
tppss-0.2.dist-info/WHEEL
tppss-0.2.dist-info/entry_points.txt
tppss-0.2.dist-info/top_level.txt
tppss-0.2.dist-info/RECORD
