Metadata-Version: 2.1
Name: tppss
Version: 0.2
Summary: Compute sunrise / sunset times taking into account local topography
Home-page: https://github.com/gvellut/tppss
Author: Guilhem Vellut
Author-email: g@vellut.com
License: UNKNOWN
Project-URL: Bug Reports, https://github.com/gvellut/tppss/issues
Project-URL: Source, https://github.com/gvellut/tppss
Keywords: sunrise dem horizon
Platform: UNKNOWN
Classifier: Development Status :: 4 - Beta
Classifier: Environment :: Console
Classifier: Intended Audience :: Science/Research
Classifier: License :: OSI Approved :: MIT License
Classifier: Natural Language :: English
Classifier: Programming Language :: Python :: 3
Classifier: Operating System :: OS Independent
Classifier: Topic :: Utilities
Classifier: Topic :: Scientific/Engineering :: GIS
Requires-Dist: numpy (==1.*)
Requires-Dist: python-dateutil (==2.*)
Requires-Dist: pyproj (==3.*)
Requires-Dist: rasterio (==1.*)
Provides-Extra: cli
Requires-Dist: click (==7.*) ; extra == 'cli'
Requires-Dist: colorama ; extra == 'cli'
Provides-Extra: dev
Requires-Dist: black ; extra == 'dev'
Requires-Dist: flake8 ; extra == 'dev'
Requires-Dist: twine ; extra == 'dev'
Requires-Dist: wheel ; extra == 'dev'
